Workbook

Sheet Rawda_procudtion_sales
A1: Date | B1: Year | C1: Month | D1: Plant | E1: Production Line | F1: Production Shift | G1: Product Type | H1: Bottles Produced | I1: Bottles Damaged | J1: Bottles Filled | K1: Warehouse | L1: Units Dispatched | M1: Dispatch Region | N1: Transport Mode | O1: Sales Channel | P1: Revenue AED | Q1: Cost AED | R1: Machine Downtime Min | S1: Energy Consumption kWh | T1: Water Usage Liters | U1: Temperature C | V1: Profit (AED) | W1: Profit Margin (%)
A2: 45292 | B2: =TEXT(A2,"yyyy") -> 2024 | C2: =TEXT(A2,"mmm") -> Jan | D2: Abu Dhabi Main | E2: Line A | F2: Morning | G2: 5 Gallon | H2: 1112 | I2: 7 | J2: 1105 | K2: Mussafah | L2: 585 | M2: Dubai | N2: Company Truck | O2: Retail | P2: 11700 | Q2: 7020.7 | R2: 6 | S2: 44.91 | T2: 16690.2 | U2: 22.4 | V2: =Rawda_procudtion_sales!P2-Rawda_procudtion_sales!Q2 -> 4679.3 | W2: =V2/P2 -> 0.39994017
A3: 45292 | B3: =TEXT(A3,"yyyy") -> 2024 | C3: =TEXT(A3,"mmm") -> Jan | D3: Abu Dhabi Main | E3: Line A | F3: Morning | G3: 330ml | H3: 4929 | I3: 107 | J3: 4822 | K3: Mussafah | L3: 2776 | M3: Dubai | N3: Company Truck | O3: Retail | P3: 3886.4 | Q3: 1953.9 | R3: 6 | S3: 89.69 | T3: 7365.03 | U3: 22.6 | V3: =Rawda_procudtion_sales!P3-Rawda_procudtion_sales!Q3 -> 1932.5 | W3: =V3/P3 -> 0.49724681
A4: 45292 | B4: =TEXT(A4,"yyyy") -> 2024 | C4: =TEXT(A4,"mmm") -> Jan | D4: Abu Dhabi Main | E4: Line A | F4: Morning | G4: 500ml | H4: 3949 | I4: 97 | J4: 3852 | K4: Dubai Hub | L4: 2249 | M4: Abu Dhabi | N4: Company Truck | O4: Wholesale | P4: 4048.2 | Q4: 2033.8 | R4: 4 | S4: 94.4 | T4: 5909.66 | U4: 23.5 | V4: =Rawda_procudtion_sales!P4-Rawda_procudtion_sales!Q4 -> 2014.4 | W4: =V4/P4 -> 0.49760387
A5: 45292 | B5: =TEXT(A5,"yyyy") -> 2024 | C5: =TEXT(A5,"mmm") -> Jan | D5: Abu Dhabi Main | E5: Line A | F5: Evening | G5: 5 Gallon | H5: 565 | I5: 5 | J5: 560 | K5: Abu Dhabi Port | L5: 305 | M5: Abu Dhabi | N5: Company Truck | O5: Subscription | P5: 6100 | Q5: 3660.5 | R5: 5 | S5: 34.17 | T5: 8485.91 | U5: 19.5 | V5: =Rawda_procudtion_sales!P5-Rawda_procudtion_sales!Q5 -> 2439.5 | W5: =V5/P5 -> 0.39991803
A6: 45292 | B6: =TEXT(A6,"yyyy") -> 2024 | C6: =TEXT(A6,"mmm") -> Jan | D6: Abu Dhabi Main | E6: Line A | F6: Evening | G6: 330ml | H6: 2640 | I6: 75 | J6: 2565 | K6: Khalifa City | L6: 1486 | M6: Dubai | N6: Third-party Logistics | O6: Wholesale | P6: 2080.4 | Q6: 1047.7 | R6: 4 | S6: 41.96 | T6: 3913.21 | U6: 21.5 | V6: =Rawda_procudtion_sales!P6-Rawda_procudtion_sales!Q6 -> 1032.7 | W6: =V6/P6 -> 0.49639492
A7: 45292 | B7: =TEXT(A7,"yyyy") -> 2024 | C7: =TEXT(A7,"mmm") -> Jan | D7: Abu Dhabi Main | E7: Line A | F7: Evening | G7: 500ml | H7: 3426 | I7: 83 | J7: 3343 | K7: Dubai Hub | L7: 1984 | M7: Abu Dhabi | N7: Third-party Logistics | O7: Retail | P7: 3571.2 | Q7: 1793.9 | R7: 6 | S7: 59.12 | T7: 5113.66 | U7: 22.2 | V7: =Rawda_procudtion_sales!P7-Rawda_procudtion_sales!Q7 -> 1777.3 | W7: =V7/P7 -> 0.49767585
A8: 45292 | B8: =TEXT(A8,"yyyy") -> 2024 | C8: =TEXT(A8,"mmm") -> Jan | D8: Abu Dhabi Main | E8: Line A | F8: Night | G8: 5 Gallon | H8: 1075 | I8: 8 | J8: 1067 | K8: Khalifa City | L8: 557 | M8: Dubai | N8: Company Truck | O8: Retail | P8: 11140 | Q8: 6684.8 | R8: 5 | S8: 38.14 | T8: 16137.74 | U8: 23 | V8: =Rawda_procudtion_sales!P8-Rawda_procudtion_sales!Q8 -> 4455.2 | W8: =V8/P8 -> 0.39992819
A9: 45292 | B9: =TEXT(A9,"yyyy") -> 2024 | C9: =TEXT(A9,"mmm") -> Jan | D9: Abu Dhabi Main | E9: Line A | F9: Night | G9: 330ml | H9: 2127 | I9: 41 | J9: 2086 | K9: Mussafah | L9: 1235 | M9: Dubai | N9: Company Truck | O9: Online | P9: 1729 | Q9: 868.6 | R9: 9 | S9: 52.58 | T9: 3217.36 | U9: 21.5 | V9: =Rawda_procudtion_sales!P9-Rawda_procudtion_sales!Q9 -> 860.4 | W9: =V9/P9 -> 0.49762869
A10: 45292 | B10: =TEXT(A10,"yyyy") -> 2024 | C10: =TEXT(A10,"mmm") -> Jan | D10: Abu Dhabi Main | E10: Line A | F10: Night | G10: 500ml | H10: 2100 | I10: 57 | J10: 2043 | K10: Khalifa City | L10: 1209 | M10: Dubai | N10: Company Truck | O10: Wholesale | P10: 2176.2 | Q10: 1093.8 | R10: 10 | S10: 55.67 | T10: 3150.77 | U10: 21 | V10: =Rawda_procudtion_sales!P10-Rawda_procudtion_sales!Q10 -> 1082.4 | W10: =V10/P10 -> 0.49738076
A11: 45292 | B11: =TEXT(A11,"yyyy") -> 2024 | C11: =TEXT(A11,"mmm") -> Jan | D11: Abu Dhabi Main | E11: Line B | F11: Morning | G11: 5 Gallon | H11: 679 | I11: 5 | J11: 674 | K11: Abu Dhabi Port | L11: 370 | M11: Al Ain | N11: Company Truck | O11: Retail | P11: 7400 | Q11: 4440.5 | R11: 7 | S11: 53.36 | T11: 10215.68 | U11: 21.3 | V11: =Rawda_procudtion_sales!P11-Rawda_procudtion_sales!Q11 -> 2959.5 | W11: =V11/P11 -> 0.39993243
A12: 45292 | B12: =TEXT(A12,"yyyy") -> 2024 | C12: =TEXT(A12,"mmm") -> Jan | D12: Abu Dhabi Main | E12: Line B | F12: Morning | G12: 330ml | H12: 4309 | I12: 108 | J12: 4201 | K12: Khalifa City | L12: 2424 | M12: Dubai | N12: Third-party Logistics | O12: Retail | P12: 3393.6 | Q12: 1707.6 | R12: 7 | S12: 87.29 | T12: 6474.16 | U12: 23.7 | V12: =Rawda_procudtion_sales!P12-Rawda_procudtion_sales!Q12 -> 1686 | W12: =V12/P12 -> 0.49681754
A13: 45292 | B13: =TEXT(A13,"yyyy") -> 2024 | C13: =TEXT(A13,"mmm") -> Jan | D13: Abu Dhabi Main | E13: Line B | F13: Morning | G13: 500ml | H13: 5190 | I13: 105 | J13: 5085 | K13: Khalifa City | L13: 3032 | M13: Abu Dhabi | N13: Company Truck | O13: Wholesale | P13: 5457.6 | Q13: 2739.3 | R13: 6 | S13: 107.34 | T13: 7735.72 | U13: 22.5 | V13: =Rawda_procudtion_sales!P13-Rawda_procudtion_sales!Q13 -> 2718.3 | W13: =V13/P13 -> 0.49807608
... A8191: 45473 | B8191: =TEXT(A8191,"yyyy") -> 2024 | C8191: =TEXT(A8191,"mmm") -> Jun | D8191: Abu Dhabi Main | E8191: Bottling Line 2 | F8191: Night | G8191: 500ml | H8191: 3890 | I8191: 51 | J8191: 3839 | K8191: Abu Dhabi Port | L8191: 2270 | M8191: Abu Dhabi | N8191: Company Truck | O8191: Retail | P8191: 4086 | Q8191: 2048.1 | R8191: 13 | S8191: 94.38 | T8191: 5839.28 | U8191: 31.7 | V8191: =Rawda_procudtion_sales!P8191-Rawda_procudtion_sales!Q8191 -> 2037.9 | W8191: =V8191/P8191 -> 0.49875184
